setup.py
epitopes/__init__.py
epitopes/amino_acid.py
epitopes/base.py
epitopes/calis.py
epitopes/common.py
epitopes/cri_tumor_antigens.py
epitopes/danafarber.py
epitopes/features.py
epitopes/fritsch_neoepitopes.py
epitopes/hiv_frahm.py
epitopes/hpv.py
epitopes/iedb.py
epitopes/imma2.py
epitopes/kmer_vectorizer.py
epitopes/mutate.py
epitopes/peptide_vectorizer.py
epitopes/reduced_alphabet.py
epitopes/reference.py
epitopes/sliding_kmer_vectorizer.py
epitopes/static_data.py
epitopes/tantigen.py
epitopes/tcga.py
epitopes/tcga_sources.py
epitopes/toxin.py
epitopes.egg-info/PKG-INFO
epitopes.egg-info/SOURCES.txt
epitopes.egg-info/dependency_links.txt
epitopes.egg-info/requires.txt
epitopes.egg-info/top_level.txt
test/test_calis.py
test/test_hiv_frahm.py
test/test_hpv.py
test/test_iedb.py
test/test_imma2.py
test/test_mutate.py
test/test_ngram.py
test/test_reference.py
test/test_tantigen.py
test/test_tcga.py