Metadata-Version: 1.1
Name: epitopes
Version: 0.3.2
Summary: Python interface to IEDB and other immune epitope data
Home-page: https://github.com/hammerlab/epitopes
Author: Alex Rubinsteyn
Author-email: alex {dot} rubinsteyn {at} mssm {dot} edu
License: http://www.apache.org/licenses/LICENSE-2.0.html
Platform: UNKNOWN
Classifier: Development Status :: 3 - Alpha
Classifier: Environment :: Console
Classifier: Operating System :: OS Independent
Classifier: Intended Audience :: Science/Research
Classifier: License :: OSI Approved :: Apache Software License
Classifier: Programming Language :: Python
Classifier: Topic :: Scientific/Engineering :: Bio-Informatics
